pygolos/__init__.py
pygolos/api.py
pygolos/api_helper.py
pygolos-1.0.1.dist-info/METADATA
pygolos-1.0.1.dist-info/RECORD
pygolos-1.0.1.dist-info/WHEEL
pygolos-1.0.1.dist-info/top_level.txt
